coinpy/__init__.py
coinpy/collector.py
coinpy/dataframe.py
coinpy/util.py
coin_py-0.0.1.dist-info/LICENSE
coin_py-0.0.1.dist-info/METADATA
coin_py-0.0.1.dist-info/WHEEL
coin_py-0.0.1.dist-info/top_level.txt
coin_py-0.0.1.dist-info/RECORD
