Metadata-Version: 2.1
Name: coin-py
Version: 0.0.1
Summary: CoinPy is an open-source project for making cryptocurrency available for everyone.
Home-page: https://github.com/Demirrr/coin-py
Author: Caglar Demir
Author-email: caglardemir8@gmail.com
License: UNKNOWN
Platform: UNKNOWN
Classifier: Programming Language :: Python :: 3.8
Classifier: License :: OSI Approved :: MIT License
Requires-Python: >=3.8.5
Requires-Dist: pandas
Requires-Dist: cbpro
Requires-Dist: matplotlib
Requires-Dist: pytest
Provides-Extra: dev
Requires-Dist: pytest (>=3.7) ; extra == 'dev'
